aminos/__init__.py
aminos/api.py
aminos/src/__init__.py
aminos/src/exception.py
aminos/src/headers.py
aminos/src/objects.py
Amino_Socket-1.0.6.dist-info/LICENSE
Amino_Socket-1.0.6.dist-info/METADATA
Amino_Socket-1.0.6.dist-info/WHEEL
Amino_Socket-1.0.6.dist-info/top_level.txt
Amino_Socket-1.0.6.dist-info/RECORD
