Metadata-Version: 2.1
Name: Amino-Socket
Version: 1.0.6
Summary: Python API to Connect Amino wss
Home-page: https://github.com/hanamixp/Amino-Socket.py.git
Author: Hanami
Author-email: hanamixp@gmail.com
License: Apache V2
Download-URL: https://github.com/Hanamixp/Amino-Socket/archive/refs/heads/main.zip
Project-URL: Source, https://github.com/Hanamixp/Amino-Socket
Keywords: aminoapps,amino,narvii,api,hanami,amino-socket
Platform: UNKNOWN
License-File: LICENSE
Requires-Dist: websocket-client
Requires-Dist: json-minify
Requires-Dist: requests
